{
    "id": "fa2362dc-cffa-4764-9b70-90d475be0c02",
    "offsetX": 101.64018291489174,
    "offsetY": -19.394324485995412,
    "zoom": 82.48206193740643,
    "gridSize": 0,
    "layers": [
        {
            "id": "1d9af8b5-858e-4253-9057-fbf3c9f2442d",
            "type": "diagram-links",
            "isSvg": true,
            "transformed": true,
            "models": {
                "921aa417-c096-4c55-916d-a629c815110a": {
                    "id": "921aa417-c096-4c55-916d-a629c815110a",
                    "type": "default",
                    "selected": false,
                    "source": "94891f48-9deb-4724-a39d-3551b000dcf6",
                    "sourcePort": "d988236c-73d4-423a-8acc-05911daede71",
                    "target": "ae350d90-0f61-4345-aa50-f6d36bc58b44",
                    "targetPort": "3fc29d39-66c3-44f5-a05b-d5bfc2f0939f",
                    "points": [
                        {
                            "id": "fe88f2a7-cba9-41bc-9a23-e13852600f1c",
                            "type": "point",
                            "x": 276.0156209570581,
                            "y": 122.78125836592525
                        },
                        {
                            "id": "9e7b046e-0959-466e-b647-06e37e3012f3",
                            "type": "point",
                            "x": 362.65625590137586,
                            "y": 237.92189040263557
                        }
                    ],
                    "labels": [],
                    "width": 3,
                    "color": "gray",
                    "curvyness": 50,
                    "selectedColor": "rgb(0,192,255)"
                },
                "6435c701-6951-42f8-a11c-9541679a3d3d": {
                    "id": "6435c701-6951-42f8-a11c-9541679a3d3d",
                    "type": "default",
                    "selected": false,
                    "source": "ae350d90-0f61-4345-aa50-f6d36bc58b44",
                    "sourcePort": "6d7a00c6-ec6f-4120-9ef5-2669c0f2075b",
                    "target": "7f7095b5-22b1-43d0-9987-d899675c810e",
                    "targetPort": "4d9bbb8d-b6c6-412f-a12c-eb415b7e918f",
                    "points": [
                        {
                            "id": "0edfd606-c080-413d-9ffe-d9e57dcab922",
                            "type": "point",
                            "x": 521.9687570116939,
                            "y": 237.92189040263557
                        },
                        {
                            "id": "1524a3db-7b04-4015-a5fd-d5feb662b8ca",
                            "type": "point",
                            "x": 683.9438576504454,
                            "y": 129.43513025456264
                        }
                    ],
                    "labels": [],
                    "width": 3,
                    "color": "gray",
                    "curvyness": 50,
                    "selectedColor": "rgb(0,192,255)"
                },
                "43b639f7-c94e-4bcf-8de8-2b0bb131a8dd": {
                    "id": "43b639f7-c94e-4bcf-8de8-2b0bb131a8dd",
                    "type": "default",
                    "selected": true,
                    "source": "ae350d90-0f61-4345-aa50-f6d36bc58b44",
                    "sourcePort": "6d7a00c6-ec6f-4120-9ef5-2669c0f2075b",
                    "target": null,
                    "targetPort": null,
                    "points": [
                        {
                            "id": "63b8a18a-c2b6-478e-8318-64c9e7a4f5bc",
                            "type": "point",
                            "x": 521.9687570116939,
                            "y": 237.92189040263557
                        },
                        {
                            "id": "56970540-1774-4599-92fb-8cd723b315d4",
                            "type": "point",
                            "x": 0,
                            "y": 0
                        }
                    ],
                    "labels": [],
                    "width": 3,
                    "color": "gray",
                    "curvyness": 50,
                    "selectedColor": "rgb(0,192,255)"
                }
            }
        },
        {
            "id": "fed3b351-5f1a-4cad-9f61-031f8a6af57e",
            "type": "diagram-nodes",
            "isSvg": false,
            "transformed": true,
            "models": {
                "94891f48-9deb-4724-a39d-3551b000dcf6": {
                    "id": "94891f48-9deb-4724-a39d-3551b000dcf6",
                    "type": "basic",
                    "selected": false,
                    "x": 179.38945802191407,
                    "y": 101.79682939853167,
                    "ports": [
                        {
                            "id": "d988236c-73d4-423a-8acc-05911daede71",
                            "type": "children",
                            "x": 271.01560653772407,
                            "y": 117.78126244611545,
                            "name": "children",
                            "alignment": "right",
                            "parentNode": "94891f48-9deb-4724-a39d-3551b000dcf6",
                            "links": [
                                "921aa417-c096-4c55-916d-a629c815110a"
                            ],
                            "in": false,
                            "label": "children"
                        }
                    ],
                    "name": "Tree Root",
                    "color": "rgb(0,204,0)",
                    "is_selected": false
                },
                "ae350d90-0f61-4345-aa50-f6d36bc58b44": {
                    "id": "ae350d90-0f61-4345-aa50-f6d36bc58b44",
                    "type": "basic",
                    "selected": false,
                    "x": 360.66273678167516,
                    "y": 216.9298918417072,
                    "ports": [
                        {
                            "id": "3fc29d39-66c3-44f5-a05b-d5bfc2f0939f",
                            "type": "parent",
                            "x": 357.65627848109034,
                            "y": 232.92189448282576,
                            "name": "parent",
                            "alignment": "left",
                            "parentNode": "ae350d90-0f61-4345-aa50-f6d36bc58b44",
                            "links": [
                                "921aa417-c096-4c55-916d-a629c815110a"
                            ],
                            "in": true,
                            "label": "parent"
                        },
                        {
                            "id": "6d7a00c6-ec6f-4120-9ef5-2669c0f2075b",
                            "type": "children",
                            "x": 516.9687055933113,
                            "y": 232.92189448282576,
                            "name": "children",
                            "alignment": "right",
                            "parentNode": "ae350d90-0f61-4345-aa50-f6d36bc58b44",
                            "links": [
                                "6435c701-6951-42f8-a11c-9541679a3d3d",
                                "43b639f7-c94e-4bcf-8de8-2b0bb131a8dd"
                            ],
                            "in": false,
                            "label": "children"
                        }
                    ],
                    "name": "ReactiveSequence",
                    "color": "rgb(0,128,255)",
                    "is_selected": false,
                    "is_subtree": false
                },
                "7f7095b5-22b1-43d0-9987-d899675c810e": {
                    "id": "7f7095b5-22b1-43d0-9987-d899675c810e",
                    "type": "basic",
                    "selected": false,
                    "x": 681.9447146753678,
                    "y": 108.44319808602478,
                    "ports": [
                        {
                            "id": "4d9bbb8d-b6c6-412f-a12c-eb415b7e918f",
                            "type": "parent",
                            "x": 678.9438802301597,
                            "y": 124.43513433475329,
                            "name": "parent",
                            "alignment": "left",
                            "parentNode": "7f7095b5-22b1-43d0-9987-d899675c810e",
                            "links": [
                                "6435c701-6951-42f8-a11c-9541679a3d3d"
                            ],
                            "in": true,
                            "label": "parent"
                        }
                    ],
                    "name": "Forward",
                    "color": "rgb(128,0,128)",
                    "is_selected": false,
                    "is_subtree": false
                },
                "6dac442e-970c-475c-b013-f11aaf5d9767": {
                    "id": "6dac442e-970c-475c-b013-f11aaf5d9767",
                    "type": "basic",
                    "selected": true,
                    "x": 681.9447146753678,
                    "y": 308.4431980860248,
                    "ports": [
                        {
                            "id": "253e9eb5-a475-46fe-8709-14c9882609f3",
                            "type": "parent",
                            "x": 678.9375163938124,
                            "y": 324.4375240614938,
                            "name": "parent",
                            "alignment": "left",
                            "parentNode": "6dac442e-970c-475c-b013-f11aaf5d9767",
                            "links": [],
                            "in": true,
                            "label": "parent"
                        }
                    ],
                    "name": "AvoidObstacle",
                    "color": "rgb(179,89,0)",
                    "is_selected": true,
                    "is_subtree": true
                }
            }
        }
    ]
}